jsim/__init__.py
jsim/Agent/Agent.py
jsim/Agent/__init__.py
jsim/Environment/Environment.py
jsim/Environment/__init__.py
jsim/Environment/HexEnvironment/HexDirections.py
jsim/Environment/HexEnvironment/HexEnvironment.py
jsim/Environment/HexEnvironment/__init__.py
jsim/Environment/HexEnvironment/HexCoords/AxialCoord.py
jsim/Environment/HexEnvironment/HexCoords/OffsetCoord.py
jsim/Environment/HexEnvironment/HexCoords/PixelCoord.py
jsim/Environment/HexEnvironment/HexCoords/__init__.py
jsim/Meta/Action.py
jsim/Meta/State.py
jsim/Meta/__init__.py
jsim/Simulation/Simulation.py
jsim/Simulation/__init__.py
jsim/Types/Coord.py
jsim/Types/Coords.py
jsim/Types/List_And_Ind.py
jsim/Types/__init__.py
jsim/Util/Map.py
jsim/Util/RasterMap.py
jsim/Util/VectorMap.py
jsim/Util/__init__.py
jsim_utils-0.1.0.dist-info/LICENSE.txt
jsim_utils-0.1.0.dist-info/METADATA
jsim_utils-0.1.0.dist-info/WHEEL
jsim_utils-0.1.0.dist-info/top_level.txt
jsim_utils-0.1.0.dist-info/RECORD
