Metadata-Version: 2.1
Name: jsim-utils
Version: 0.1.0
Summary: Simulation environment for SAR
Home-page: https://jsim.janhendrikewers.uk
Author: iwishiwasaneagle
Author-email: jh.ewers@gmail.com
License: GPL-3.0-or-later
Project-URL: Documentation, https://jsim.janhendrikewers.uk/api/modules.html
Project-URL: Changelog, https://jsim.janhendrikewers.uk/changelog.html
Project-URL: Source, https://github.com/iwishiwasaneagle/jsim
Project-URL: Tracker, https://github.com/iwishiwasaneagle/jsim/issues
Project-URL: Download, https://github.com/iwishiwasaneagle/jsim/releases
Platform: Linux
Classifier: Development Status :: 3 - Alpha
Classifier: Programming Language :: Python :: 3
Classifier: License :: OSI Approved :: GNU General Public License v3 or later (GPLv3+)
Classifier: Natural Language :: English
Classifier: Operating System :: Unix
Classifier: Topic :: Scientific/Engineering
License-File: LICENSE.txt
Requires-Dist: loguru
Requires-Dist: matplotlib
Requires-Dist: numpy
Requires-Dist: rtree
Requires-Dist: rasterio
Requires-Dist: geopandas
Requires-Dist: shapely
Requires-Dist: tqdm
Requires-Dist: importlib-metadata ; python_version < "3.8"
Provides-Extra: test
Requires-Dist: setuptools ; extra == 'test'
Requires-Dist: pytest ; extra == 'test'
Requires-Dist: pytest-cov ; extra == 'test'
Requires-Dist: tox ; extra == 'test'
